mcp_skills/VERSION
mcp_skills/__init__.py
mcp_skills/py.typed
mcp_skills/cli/__init__.py
mcp_skills/cli/config_menu.py
mcp_skills/cli/main.py
mcp_skills/cli/commands/__init__.py
mcp_skills/cli/commands/ask.py
mcp_skills/cli/commands/build_skill.py
mcp_skills/cli/commands/config.py
mcp_skills/cli/commands/demo.py
mcp_skills/cli/commands/discover.py
mcp_skills/cli/commands/doctor.py
mcp_skills/cli/commands/enrich.py
mcp_skills/cli/commands/enrich_hook.py
mcp_skills/cli/commands/index.py
mcp_skills/cli/commands/info.py
mcp_skills/cli/commands/install.py
mcp_skills/cli/commands/list_skills.py
mcp_skills/cli/commands/mcp_server.py
mcp_skills/cli/commands/recent.py
mcp_skills/cli/commands/recommend.py
mcp_skills/cli/commands/repo.py
mcp_skills/cli/commands/search.py
mcp_skills/cli/commands/setup.py
mcp_skills/cli/commands/stats.py
mcp_skills/cli/shared/__init__.py
mcp_skills/cli/shared/console.py
mcp_skills/hooks/__init__.py
mcp_skills/mcp/__init__.py
mcp_skills/mcp/server.py
mcp_skills/mcp/tools/__init__.py
mcp_skills/mcp/tools/find_tool.py
mcp_skills/mcp/tools/skill_tool.py
mcp_skills/mcp/tools/skill_tools_legacy.py
mcp_skills/models/__init__.py
mcp_skills/models/config.py
mcp_skills/models/repository.py
mcp_skills/models/skill.py
mcp_skills/services/__init__.py
mcp_skills/services/agent_detector.py
mcp_skills/services/agent_installer.py
mcp_skills/services/auto_updater.py
mcp_skills/services/github_discovery.py
mcp_skills/services/llm_service.py
mcp_skills/services/mcp_server.py
mcp_skills/services/metadata_store.py
mcp_skills/services/prompt_enricher.py
mcp_skills/services/py_mcp_installer_wrapper.py
mcp_skills/services/repository_manager.py
mcp_skills/services/skill_builder.py
mcp_skills/services/skill_manager.py
mcp_skills/services/toolchain_detector.py
mcp_skills/services/indexing/__init__.py
mcp_skills/services/indexing/engine.py
mcp_skills/services/indexing/graph_store.py
mcp_skills/services/indexing/hybrid_search.py
mcp_skills/services/indexing/vector_store.py
mcp_skillset-0.8.1.dist-info/licenses/LICENSE
mcp_skillset-0.8.1.dist-info/METADATA
mcp_skillset-0.8.1.dist-info/WHEEL
mcp_skillset-0.8.1.dist-info/entry_points.txt
mcp_skillset-0.8.1.dist-info/top_level.txt
mcp_skillset-0.8.1.dist-info/RECORD
