Metadata-Version: 2.4
Name: mcp-skillset
Version: 0.8.1
Summary: Dynamic RAG-powered skills for code assistants via Model Context Protocol
Author-email: MCP Skills Contributors <contact@example.com>
Maintainer: MCP Skills Team
License: MIT
Project-URL: Homepage, https://github.com/bobmatnyc/mcp-skillset
Project-URL: Repository, https://github.com/bobmatnyc/mcp-skillset.git
Project-URL: Issues, https://github.com/bobmatnyc/mcp-skillset/issues
Project-URL: Documentation, https://github.com/bobmatnyc/mcp-skillset/blob/main/README.md
Keywords: mcp,model-context-protocol,rag,skills,vector-search,knowledge-graph
Classifier: Development Status :: 3 - Alpha
Classifier: Intended Audience :: Developers
Classifier: License :: OSI Approved :: MIT License
Classifier: Programming Language :: Python :: 3
Classifier: Programming Language :: Python :: 3.11
Classifier: Programming Language :: Python :: 3.12
Classifier: Programming Language :: Python :: 3.13
Classifier: Topic :: Software Development :: Libraries :: Python Modules
Classifier: Topic :: Scientific/Engineering :: Artificial Intelligence
Requires-Python: >=3.11
License-File: LICENSE
Requires-Dist: click>=8.0
Requires-Dist: pydantic>=2.0
Requires-Dist: pydantic-settings>=2.0
Requires-Dist: pyyaml>=6.0
Requires-Dist: rich>=13.0.0
Requires-Dist: mcp>=0.1.0
Requires-Dist: chromadb>=0.4.0
Requires-Dist: sentence-transformers>=2.2.0
Requires-Dist: networkx>=3.0
Requires-Dist: sqlalchemy>=2.0
Requires-Dist: gitpython>=3.1.0
Requires-Dist: httpx>=0.27.0
Requires-Dist: python-frontmatter>=1.0.0
Requires-Dist: watchdog>=3.0.0
Requires-Dist: questionary>=2.0.1
Requires-Dist: pyperclip>=1.8.2
Requires-Dist: jinja2>=3.1.0
Provides-Extra: dev
Requires-Dist: pytest>=7.0; extra == "dev"
Requires-Dist: pytest-cov>=4.0; extra == "dev"
Requires-Dist: pytest-asyncio>=0.21.0; extra == "dev"
Requires-Dist: pytest-benchmark>=4.0.0; extra == "dev"
Requires-Dist: ruff>=0.8.0; extra == "dev"
Requires-Dist: mypy>=1.0.0; extra == "dev"
Requires-Dist: black>=24.0.0; extra == "dev"
Requires-Dist: detect-secrets>=1.4.0; extra == "dev"
Requires-Dist: safety>=3.0.0; extra == "dev"
Requires-Dist: pip-audit>=2.6.0; extra == "dev"
Requires-Dist: bandit>=1.7.0; extra == "dev"
Requires-Dist: types-PyYAML>=6.0.0; extra == "dev"
Requires-Dist: types-click>=7.1.0; extra == "dev"
Provides-Extra: qdrant
Requires-Dist: qdrant-client>=1.7.0; extra == "qdrant"
Provides-Extra: neo4j
Requires-Dist: neo4j>=5.0.0; extra == "neo4j"
Dynamic: license-file
